{"Новинки": [["Айс Кофе Карамель", "от 135 ₽"], ["Айс Кофе Карамель Миндальный", "от 195 ₽"], ["Апельсиновый Раф", "от 179 ₽"], ["Айс Кофе Карамель Кокосовый", "от 195 ₽"], ["Биг Спешиал Три Сыра", "от 299 ₽"], ["Пирожок Пряное яблоко", "от 65 ₽"], ["Шримп Ролл", "от 229 ₽"], ["Айс Де Люкс Шоколадный брауни", "от 109 ₽"], ["Айс Де Люкс Ананас", "от 119 ₽"], ["Лимонад Спелая слива-Красная смородина", "от 89 ₽"], ["Фанта Мангуава в бутылке (0,5 л)", "от 109 ₽"], ["Айс Кофе Кленовый Пекан 0,3 л", "от 135 ₽"], ["Айс Кофе Кленовый Пекан Миндальный 0,3 л", "от 195 ₽"], ["Айс Кофе Кленовый Пекан Кокосовый 0,3 л", "от 195 ₽"], ["Капучино Кленовый Пекан 0,3 л", "от 135 ₽"], ["Картофельные Дольки Средние", "от 95 ₽"], ["Картофельные Дольки Большие", "от 119 ₽"], ["Гранд Фри Средний", "от 85 ₽"], ["Гранд Фри Большой", "от 99 ₽"]], "Популярное": [["Гранд Де Люкс", "от 185 ₽"], ["Биг Спешиал", "от 269 ₽"], ["Двойной Чизбургер", "от 129 ₽"], ["Чикен Премьер", "от 149 ₽"], ["Наггетсы (6 шт.)", "от 69 ₽"], ["Пирожок Вишневый", "от 59 ₽"], ["Фреш Маффин", "от 129 ₽"], ["Двойной Маффин с яйцом и свиной котлетой", "от 165 ₽"], ["Тост с ветчиной", "от 65 ₽"], ["Чикен Фреш Маффин", "от 119 ₽"]], "Комбо Обед": [["Биг Спешиал Три Сыра Комбо", "от 381 ₽"], ["Биг Спешиал Джуниор Комбо", "от 299 ₽"], ["Шримп Ролл Комбо", "от 330 ₽"], ["Биг Спешиал Ролл Комбо", "от 293 ₽"], ["Двойной Биг Спешиал Комбо", "от 436 ₽"], ["Биг Спешиал Комбо", "от 351 ₽"], ["Цезарь Ролл Комбо", "от 272 ₽"], ["Цезарь Ролл с беконом Комбо", "от 292 ₽"], ["Гранд Де Люкс Комбо", "от 272 ₽"], ["Двойной Гранд Комбо", "от 329 ₽"], ["Гранд Комбо", "от 240 ₽"], ["Двойной Чизбургер Комбо", "от 210 ₽"], ["Чикен Премьер Комбо", "от 234 ₽"], ["Чикен Хит Комбо", "от 184 ₽"], ["Двойной Фиш Бургер Комбо", "от 316 ₽"], ["Фиш Бургер Комбо", "от 265 ₽"], ["Креветки (9 шт.) Комбо", "от 436 ₽"], ["Креветки (6 шт.) Комбо", "от 336 ₽"], ["Наггетсы (9 шт.) Комбо", "от 197 ₽"], ["Наггетсы (6 шт.) Комбо", "от 160 ₽"], ["Стрипсы (7 шт.) Комбо", "от 295 ₽"], ["Стрипсы (5 шт.) Комбо", "от 245 ₽"], ["Стрипсы (3 шт.) Комбо", "от 196 ₽"], ["Куриные крылышки (7 шт.) Комбо", "от 345 ₽"], ["Куриные крылышки (5 шт.) Комбо", "от 281 ₽"], ["Куриные крылышки (3 шт.) Комбо", "от 231 ₽"]], "Бургеры и роллы": [["Биг Спешиал Три Сыра", "от 299 ₽"], ["Шримп Ролл", "от 229 ₽"], ["Биг Спешиал Джуниор", "от 209 ₽"], ["Гранд Де Люкс", "от 185 ₽"], ["Двойной Гранд", "от 239 ₽"], ["Гранд", "от 164 ₽"], ["Двойной Биг Спешиал", "от 355 ₽"], ["Биг Спешиал", "от 269 ₽"], ["Двойной Чизбургер", "от 129 ₽"], ["Чизбургер", "от 59 ₽"], ["Гамбургер", "от 55 ₽"], ["Чикен Хит", "от 109 ₽"], ["Чикен Премьер", "от 149 ₽"], ["Чикенбургер", "от 59 ₽"], ["Двойной Фиш Бургер", "от 215 ₽"], ["Фиш Бургер", "от 165 ₽"], ["Цезарь Ролл с беконом", "от 199 ₽"], ["Биг Спешиал Ролл", "от 199 ₽"], ["Цезарь Ролл", "от 179 ₽"]], "Картофель, стартеры и салаты": [["Снэк Бокс с крыльями", "от 239 ₽"], ["Большой Снэк Бокс со Стрипсами", "от 445 ₽"], ["Большой Снэк Бокс с Крыльями", "от 469 ₽"], ["Картофельные Дольки Средние", "от 95 ₽"], ["Картофель Фри Маленький", "от 59 ₽"], ["Гранд Фри Маленький", "от 59 ₽"], ["Картофель по-деревенски Средний", "от 95 ₽"], ["Большой Снэк Бокс с Крыльями", "от 469 ₽"], ["Морковные палочки", "от 65 ₽"], ["Яблочные дольки", "от 65 ₽"], ["Большой Снэк Бокс со Стрипсами", "от 445 ₽"], ["Снэк Бокс с крыльями", "от 239 ₽"], ["Куриные крылышки (3 шт.)", "от 135 ₽"], ["Наггетсы (4 шт.)", "от 59 ₽"], ["Стрипсы (3 шт.)", "от 99 ₽"], ["Креветки (4 шт.)", "от 189 ₽"], ["Сырные палочки", "от 99 ₽"], ["Салат Цезарь", "от 179 ₽"], ["Салат Цезарь с креветками", "от 239 ₽"], ["Овощной салат", "от 109 ₽"], ["Овощной салат", "от 109 ₽"]], "Напитки": [["Айс Кофе Карамель", "от 135 ₽"], ["Айс Кофе Карамель Миндальный", "от 195 ₽"], ["Апельсиновый Раф", "от 179 ₽"], ["Айс Кофе Карамель Кокосовый", "от 195 ₽"], ["Лимонад Спелая слива-Красная смородина", "от 89 ₽"], ["Фанта Мангуава в бутылке (0,5 л)", "от 109 ₽"], ["Айс Кофе Кленовый Пекан 0,3 л", "от 135 ₽"], ["Айс Кофе Кленовый Пекан Миндальный 0,3 л", "от 195 ₽"], ["Айс Кофе Кленовый Пекан Кокосовый 0,3 л", "от 195 ₽"], ["Капучино Кленовый Пекан 0,3 л", "от 135 ₽"], ["Миндальный Латте 0,27 л", "от 165 ₽"], ["Кокосовый Латте 0,27 л", "от 165 ₽"], ["Латте 0,3 л", "от 105 ₽"], ["Миндальный Флэт Уайт 0,24 л", "от 209 ₽"], ["Кокосовый Флэт Уайт 0,24 л", "от 209 ₽"], ["Флэт Уайт 0,3 л", "от 149 ₽"], ["Миндальный Пряный Чай Латте 0,27 л", "от 209 ₽"], ["Кокосовый Пряный Чай Латте 0,27 л", "от 209 ₽"], ["Пряный Чай Латте 0,27 л", "от 149 ₽"], ["Американо 0,2 л", "от 55 ₽"], ["Венский Кофе 0,25 л", "от 149 ₽"], ["Горячий Шоколад 0,3 л", "от 179 ₽"], ["Мокко 0,3 л", "от 149 ₽"], ["Раф 0,3 л", "от 149 ₽"], ["Чай Зеленый с Жасмином 0,4 л", "от 99 ₽"], ["Чай Черный Эрл Грей 0,4 л", "от 99 ₽"], ["Чай Кенийский 0,4 л", "от 99 ₽"], ["Чай Черный с Чабрецом 0,4 л", "от 99 ₽"], ["Чай Хуго Коктейль 0,4 л", "от 99 ₽"], ["Двойной Эспрессо", "от 69 ₽"], ["Миндальный Капучино 0,17 л", "от 125 ₽"], ["Кокосовый Капучино 0,17 л", "от 125 ₽"], ["Капучино 0,2 л", "от 65 ₽"], ["Фраппе Карамельный 0,33 л", "от 159 ₽"], ["Фраппе Мокко 0,33 л", "от 159 ₽"], ["Добрый Кола 0,25 л", "от 79 ₽"], ["Добрый Апельсин 0,25 л", "от 79 ₽"], ["Добрый Лимон-Лайм 0,25 л", "от 79 ₽"], ["Липтон Зеленый 0,25 л", "от 69 ₽"], ["Липтон Лимон 0,25 л", "от 69 ₽"], ["Фанта в бутылке (0,5 л)", "от 109 ₽"], ["Спрайт в бутылке (0,5 л)", "от 109 ₽"], ["Фанта без сахара в бутылке (0,5 л)", "от 109 ₽"], ["Спрайт без сахара в бутылке (0,5 л)", "от 109 ₽"], ["Питьевая вода Аква Минерале газированная 0,5 л", "от 89 ₽"], ["Питьевая вода Аква Минерале негазированная 0,5 л", "от 89 ₽"], ["Яблочный сок 0,3 л", "от 79 ₽"], ["Апельсиновый сок 0,3 л", "от 79 ₽"], ["Коктейль Ванильный 0,25 л", "от 69 ₽"], ["Коктейль Клубничный 0,25 л", "от 69 ₽"], ["Коктейль Шоколадный 0,25 л", "от 69 ₽"], ["Чай Черный 0,2 л", "от 55 ₽"], ["Чай Зеленый 0,2 л", "от 55 ₽"], ["Капучино 0,2 л", "от 65 ₽"], ["Латте 0,3 л", "от 105 ₽"], ["Американо 0,2 л", "от 55 ₽"], ["Кофе Глясе 0,28 л", "от 109 ₽"], ["Двойной Эспрессо", "от 69 ₽"], ["Фанта Маленькая", "от 69 ₽"], ["Спрайт Маленький", "от 69 ₽"]], "Завтрак": [["Клубничный Чизкейк", "от 175 ₽"], ["Торт Шоколадный", "от 175 ₽"], ["Пирожное Черный лес", "от 175 ₽"], ["Тирамису", "от 165 ₽"], ["Премиальный Яблочный пирог", "от 185 ₽"], ["Торт Миндальный", "от 175 ₽"], ["Чизкейк Карамельный", "от 175 ₽"], ["Торт Рикотта с грушей", "от 175 ₽"], ["Эклер Ванильный", "от 140 ₽"], ["Макарони (1 шт.)", "от 75 ₽"], ["Донат с шоколадным кремом", "от 89 ₽"], ["Печенье Клюква-кокос", "от 79 ₽"], ["Печенье шоколадное с кусочками шоколада", "от 79 ₽"], ["Кленовый пекан", "от 119 ₽"], ["Улитка с карамелью", "от 119 ₽"], ["Круассан", "от 99 ₽"], ["Круассан с ветчиной и сыром", "от 139 ₽"], ["Чиабатта с тунцом", "от 185 ₽"], ["Чиабатта с ветчиной и сыром", "от 175 ₽"], ["Сырники", "от 150 ₽"], ["Киш с курицей и грибами", "от 150 ₽"], ["Айс Кофе Карамель", "от 135 ₽"], ["Айс Кофе Карамель Миндальный", "от 195 ₽"], ["Апельсиновый Раф", "от 179 ₽"], ["Айс Кофе Карамель Кокосовый", "от 195 ₽"], ["Пирожок Пряное яблоко", "от 65 ₽"], ["Айс Де Люкс Шоколадный брауни", "от 109 ₽"], ["Айс Де Люкс Ананас", "от 119 ₽"], ["Лимонад Спелая слива-Красная смородина", "от 89 ₽"], ["Фанта Мангуава в бутылке (0,5 л)", "от 109 ₽"], ["Айс Кофе Кленовый Пекан 0,3 л", "от 135 ₽"], ["Айс Кофе Кленовый Пекан Миндальный 0,3 л", "от 195 ₽"], ["Айс Кофе Кленовый Пекан Кокосовый 0,3 л", "от 195 ₽"], ["Капучино Кленовый Пекан 0,3 л", "от 135 ₽"], ["Яичница с сыром Комбо", "от 241 ₽"], ["Яичница с ветчиной Комбо", "от 241 ₽"], ["Яичница с беконом Комбо", "от 241 ₽"], ["Омлет с сыром Комбо", "от 241 ₽"], ["Омлет с ветчиной Комбо", "от 241 ₽"], ["Омлет с беконом Комбо", "от 241 ₽"], ["Наггетсы (6 шт.) Комбо", "от 160 ₽"], ["Наггетсы (9 шт.) Комбо", "от 197 ₽"], ["Пирожок Вишневый", "от 59 ₽"], ["Яблочное пюре", "от 65 ₽"], ["Миндальный Латте 0,27 л", "от 165 ₽"], ["Кокосовый Латте 0,27 л", "от 165 ₽"], ["Латте 0,3 л", "от 105 ₽"], ["Миндальный Флэт Уайт 0,24 л", "от 209 ₽"], ["Кокосовый Флэт Уайт 0,24 л", "от 209 ₽"], ["Флэт Уайт 0,3 л", "от 149 ₽"], ["Миндальный Пряный Чай Латте 0,27 л", "от 209 ₽"], ["Кокосовый Пряный Чай Латте 0,27 л", "от 209 ₽"], ["Пряный Чай Латте 0,27 л", "от 149 ₽"], ["Американо 0,2 л", "от 55 ₽"], ["Венский Кофе 0,25 л", "от 149 ₽"], ["Яичница Комбо", "от 211 ₽"], ["Горячий Шоколад 0,3 л", "от 179 ₽"], ["Омлет Комбо", "от 211 ₽"], ["Двойной Маффин с яйцом и свиной котлетой Комбо", "от 259 ₽"], ["Двойной Фреш Маффин Комбо", "от 256 ₽"], ["Мокко 0,3 л", "от 149 ₽"], ["Фреш Ролл Комбо", "от 248 ₽"], ["Фреш Маффин Комбо", "от 230 ₽"], ["Маффин с яйцом и свиной котлетой Комбо", "от 218 ₽"], ["Маффин со свиной котлетой Комбо", "от 205 ₽"], ["Раф 0,3 л", "от 149 ₽"], ["Чикен Фреш Маффин Комбо", "от 219 ₽"], ["Маффин с яйцом и ветчиной Комбо", "от 179 ₽"], ["Маффин с яйцом и сыром Комбо", "от 189 ₽"], ["Маффин с яйцом и беконом Комбо", "от 205 ₽"], ["Чай Зеленый с Жасмином 0,4 л", "от 99 ₽"], ["Фреш Маффин", "от 129 ₽"], ["Чай Черный Эрл Грей 0,4 л", "от 99 ₽"], ["Двойной Маффин с яйцом и свиной котлетой", "от 165 ₽"], ["Тост с ветчиной", "от 65 ₽"], ["Чикен Фреш Маффин", "от 119 ₽"], ["Чай Кенийский 0,4 л", "от 99 ₽"], ["Маффин с яйцом и свиной котлетой", "от 115 ₽"], ["Двойной Фреш Маффин", "от 159 ₽"], ["Чай Черный с Чабрецом 0,4 л", "от 99 ₽"], ["Маффин с яйцом и беконом", "от 105 ₽"], ["Маффин с яйцом и ветчиной", "от 105 ₽"], ["Чай Хуго Коктейль 0,4 л", "от 99 ₽"], ["Маффин с яйцом и сыром", "от 89 ₽"], ["Маффин со свиной котлетой", "от 105 ₽"], ["Тост с сыром", "от 55 ₽"], ["Двойной Эспрессо", "от 69 ₽"], ["Фреш Ролл", "от 145 ₽"], ["Миндальный Капучино 0,17 л", "от 125 ₽"], ["Яичница с сыром", "от 145 ₽"], ["Яичница с ветчиной", "от 145 ₽"], ["Яичница с беконом", "от 145 ₽"], ["Яичница", "от 115 ₽"], ["Омлет с сыром", "от 145 ₽"], ["Омлет с ветчиной", "от 145 ₽"], ["Омлет с беконом", "от 145 ₽"], ["Омлет", "от 115 ₽"], ["Кокосовый Капучино 0,17 л", "от 125 ₽"], ["Капучино 0,2 л", "от 65 ₽"], ["Фраппе Карамельный 0,33 л", "от 159 ₽"], ["Фраппе Мокко 0,33 л", "от 159 ₽"], ["Добрый Кола 0,25 л", "от 79 ₽"], ["Добрый Апельсин 0,25 л", "от 79 ₽"], ["Добрый Лимон-Лайм 0,25 л", "от 79 ₽"], ["Блины", "от 105 ₽"], ["Наггетсы (6 шт.)", "от 69 ₽"], ["Наггетсы (9 шт.)", "от 99 ₽"], ["Липтон Зеленый 0,25 л", "от 69 ₽"], ["Рулетики с творогом", "от 85 ₽"], ["Вафельный Рожок", "от 39 ₽"], ["Мороженое Карамельное", "от 84 ₽"], ["Мороженое Шоколадное", "от 84 ₽"], ["Мороженое Клубничное", "от 84 ₽"], ["Пирожок Черная смородина", "от 65 ₽"], ["Джем клубничный", "от 30 ₽"], ["Липтон Лимон 0,25 л", "от 69 ₽"], ["Джем Абрикосовый", "от 30 ₽"], ["Мёд", "от 30 ₽"], ["Фанта в бутылке (0,5 л)", "от 109 ₽"], ["Спрайт в бутылке (0,5 л)", "от 109 ₽"], ["Фанта без сахара в бутылке (0,5 л)", "от 109 ₽"], ["Спрайт без сахара в бутылке (0,5 л)", "от 109 ₽"], ["Питьевая вода Аква Минерале газированная 0,5 л", "от 89 ₽"], ["Питьевая вода Аква Минерале негазированная 0,5 л", "от 89 ₽"], ["Яблочный сок 0,3 л", "от 79 ₽"], ["Апельсиновый сок 0,3 л", "от 79 ₽"], ["Коктейль Ванильный 0,25 л", "от 69 ₽"], ["Коктейль Клубничный 0,25 л", "от 69 ₽"], ["Коктейль Шоколадный 0,25 л", "от 69 ₽"], ["Чай Черный 0,2 л", "от 55 ₽"], ["Чай Зеленый 0,2 л", "от 55 ₽"], ["Капучино 0,2 л", "от 65 ₽"], ["Латте 0,3 л", "от 105 ₽"], ["Американо 0,2 л", "от 55 ₽"], ["Кофе Глясе 0,28 л", "от 109 ₽"], ["Двойной Эспрессо", "от 69 ₽"], ["Фанта Маленькая", "от 69 ₽"], ["Спрайт Маленький", "от 69 ₽"]], "Десерты и выпечка": [["Клубничный Чизкейк", "от 175 ₽"], ["Торт Шоколадный", "от 175 ₽"], ["Пирожное Черный лес", "от 175 ₽"], ["Тирамису", "от 165 ₽"], ["Премиальный Яблочный пирог", "от 185 ₽"], ["Торт Миндальный", "от 175 ₽"], ["Чизкейк Карамельный", "от 175 ₽"], ["Торт Рикотта с грушей", "от 175 ₽"], ["Эклер Ванильный", "от 140 ₽"], ["Макарони (1 шт.)", "от 75 ₽"], ["Донат с шоколадным кремом", "от 89 ₽"], ["Печенье Клюква-кокос", "от 79 ₽"], ["Печенье шоколадное с кусочками шоколада", "от 79 ₽"], ["Кленовый пекан", "от 119 ₽"], ["Улитка с карамелью", "от 119 ₽"], ["Круассан", "от 99 ₽"], ["Круассан с ветчиной и сыром", "от 139 ₽"], ["Чиабатта с тунцом", "от 185 ₽"], ["Чиабатта с ветчиной и сыром", "от 175 ₽"], ["Сырники", "от 150 ₽"], ["Киш с курицей и грибами", "от 150 ₽"], ["Пирожок Пряное яблоко", "от 65 ₽"], ["Айс Де Люкс Шоколадный брауни", "от 109 ₽"], ["Айс Де Люкс Ананас", "от 119 ₽"], ["Пирожок Вишневый", "от 59 ₽"], ["Яблочное пюре", "от 65 ₽"], ["Вафельный Рожок", "от 39 ₽"], ["Мороженое Карамельное", "от 84 ₽"], ["Мороженое Шоколадное", "от 84 ₽"], ["Мороженое Клубничное", "от 84 ₽"], ["Пирожок Черная смородина", "от 65 ₽"]], "Соусы": []}